koheron/__init__.py
koheron/alpha250.py
koheron/cli.py
koheron/koheron.py
koheron/version.py
koheron-0.24.0.dist-info/METADATA
koheron-0.24.0.dist-info/WHEEL
koheron-0.24.0.dist-info/entry_points.txt
koheron-0.24.0.dist-info/top_level.txt
koheron-0.24.0.dist-info/RECORD
