Metadata-Version: 2.1
Name: koheron
Version: 0.24.0
Summary: Koheron Python Library
Home-page: https://github.com/Koheron/koheron-sdk
Author: Koheron
Author-email: hello@koheron.com
License: MIT
Keywords: FPGA Linux Instrumentation
Classifier: Programming Language :: Python :: 2.7
Classifier: Programming Language :: Python :: 3.5
Requires-Dist: requests
Requires-Dist: Click
